ColabTurtlePlus/Turtle.py
ColabTurtlePlus/__init__.py
ColabTurtlePlus-2.0.1.dist-info/LICENSE
ColabTurtlePlus-2.0.1.dist-info/METADATA
ColabTurtlePlus-2.0.1.dist-info/WHEEL
ColabTurtlePlus-2.0.1.dist-info/top_level.txt
ColabTurtlePlus-2.0.1.dist-info/RECORD
