Metadata-Version: 2.1
Name: ColabTurtlePlus
Version: 2.0.1
Summary: An HTML based Turtle implementation with classes for Google Colab and Jupyter Labs
Home-page: https://github.com/mathriddle/ColabTurtlePlus
Author: Larry Riddle
Author-email: lriddle@agnesscott.edu
License: MIT
Project-URL: Bug Tracker, https://github.com/mathriddle/ColabTurtlePlus/issues
Project-URL: Examples, https://github.com/mathriddle/ColabTurtlePlus/tree/main/examples_version2
Project-URL: Documentation, https://larryriddle.agnesscott.org/ColabTurtlePlus/documentation2.html
Platform: UNKNOWN
Classifier: License :: OSI Approved :: MIT License
Classifier: Programming Language :: Python :: 3
License-File: LICENSE
